litetts/__init__.py
litetts/driver.py
litetts/engine.py
litetts/six.py
litetts/voice.py
litetts/drivers/__init__.py
litetts/drivers/_espeak.py
litetts/drivers/dummy.py
litetts/drivers/espeak.py
litetts/drivers/nsss.py
litetts/drivers/sapi5.py
tests/__init__.py
tests/driver.py
tests/engine.py
tests/six.py
tests/voice.py
tests/drivers/__init__.py
tests/drivers/_espeak.py
tests/drivers/dummy.py
tests/drivers/espeak.py
tests/drivers/nsss.py
tests/drivers/sapi5.py
litetts-0.4.0.dist-info/LICENSE
litetts-0.4.0.dist-info/METADATA
litetts-0.4.0.dist-info/WHEEL
litetts-0.4.0.dist-info/top_level.txt
litetts-0.4.0.dist-info/RECORD
